{
    "common": {
        "name": "notification-manager",
        "version": "0.0.1",
        "news": {
            "0.0.1": {
                "en": "initial release",
                "de": "Erstveröffentlichung",
                "ru": "Начальная версия",
                "pt": "lançamento inicial",
                "nl": "Eerste uitgave",
                "fr": "Première version",
                "it": "Versione iniziale",
                "es": "Versión inicial",
                "pl": "Pierwsze wydanie",
                "uk": "Початкова версія",
                "zh-cn": "首次出版"
            }
        },
        "title": "Notification Manager",
        "titleLang": {
            "en": "Notification Manager",
            "de": "Benachrichtigungsmanager",
            "ru": "Менеджер уведомлений",
            "pt": "Gerenciador de notificações",
            "nl": "Meldingsbeheerder",
            "fr": "Gestionnaire de notifications",
            "it": "Responsabile delle notifiche",
            "es": "Administrador de notificaciones",
            "pl": "Menedżer powiadomień",
            "uk": "Менеджер сповіщень",
            "zh-cn": "通知管理器"
        },
        "desc": {
            "en": "Manage ioBroker notifications, e.g. by sending them as messages",
            "de": "Verwalten Sie ioBroker-Benachrichtigungen, z. indem Sie sie als Nachrichten versenden",
            "ru": "Управление уведомлениями ioBroker, например. отправив их в виде сообщений",
            "pt": "Gerenciar notificações do ioBroker, por exemplo enviando-os como mensagens",
            "nl": "Beheer ioBroker-meldingen, b.v. door ze als berichten te verzenden",
            "fr": "Gérer les notifications ioBroker, par ex. en les envoyant sous forme de messages",
            "it": "Gestisci le notifiche ioBroker, ad es. inviandoli come messaggi",
            "es": "Administre las notificaciones de ioBroker, p. enviándolos como mensajes",
            "pl": "Zarządzaj powiadomieniami ioBroker, np. wysyłając je jako wiadomości",
            "uk": "Керуйте сповіщеннями ioBroker, напр. надсилаючи їх як повідомлення",
            "zh-cn": "管理 ioBroker 通知，例如通过将它们作为消息发送"
        },
        "authors": [
            "foxriver76 <moritz.heusinger@gmail.com>"
        ],
        "keywords": [
            "notifications",
            "messages"
        ],
        "license": "MIT",
        "platform": "Javascript/Node.js",
        "main": "build/main.js",
        "icon": "notification-manager.png",
        "enabled": true,
        "extIcon": "https://raw.githubusercontent.com/foxriver76/ioBroker.notification-manager/main/admin/notification-manager.png",
        "readme": "https://github.com/foxriver76/ioBroker.notification-manager/blob/main/README.md",
        "loglevel": "info",
        "mode": "daemon",
        "type": "utility",
        "compact": true,
        "connectionType": "local",
        "dataSource": "push",
        "messagebox": true,
        "adminUI": {
            "config": "materialize"
        },
        "eraseOnUpload": true,
        "dependencies": [
            {
                "js-controller": ">=3.3.22"
            }
        ],
        "globalDependencies": [
            {
                "admin": ">=5.0.0"
            }
        ]
    },
    "native": {
        "categories": {},
        "fallback": {
            "info": {
                "firstAdapter": "",
                "secondAdapter": ""
            },
            "notify": {
                "firstAdapter": "",
                "secondAdapter": ""
            },
            "alert": {
                "firstAdapter": "",
                "secondAdapter": ""
            }
        }
    },
    "objects": [],
    "instanceObjects": []
}
